<?xml version="1.0" ?>
<annotation>
  <folder>VOC</folder>
  <filename>0079.jpg</filename>
  <source>
    <database>roboflow.ai</database>
  </source>
  <size>
    <width>183</width>
    <height>126</height>
    <depth>3</depth>
  </size>
  <segmented>0</segmented>
  <object>
    <name>number plate</name>
    <bndbox>
      <xmin>39</xmin>
      <ymin>30</ymin>
      <xmax>144</xmax>
      <ymax>83</ymax>
    </bndbox>
    <polygon>
      <x1>141</x1>
      <y1>32</y1>
      <x2>131</x2>
      <y2>30</y2>
      <x3>127</x3>
      <y3>32</y3>
      <x4>39</x4>
      <y4>35</y4>
      <x5>42</x5>
      <y5>82</y5>
      <x6>71</x6>
      <y6>83</y6>
      <x7>143</x7>
      <y7>79</y7>
      <x8>144</x8>
      <y8>66</y8>
    </polygon>
  </object>
  <object>
    <name>number plate</name>
    <bndbox>
      <xmin>0</xmin>
      <ymin>23</ymin>
      <xmax>182</xmax>
      <ymax>94</ymax>
    </bndbox>
    <polygon>
      <x1>182</x1>
      <y1>30</y1>
      <x2>179</x2>
      <y2>27</y2>
      <x3>168</x3>
      <y3>23</y3>
      <x4>122</x4>
      <y4>23</y4>
      <x5>28</x5>
      <y5>27</y5>
      <x6>7</x6>
      <y6>31</y6>
      <x7>0</x7>
      <y7>37</y7>
      <x8>0</x8>
      <y8>94</y8>
      <x9>45</x9>
      <y9>91</y9>
      <x10>102</x10>
      <y10>90</y10>
      <x11>119</x11>
      <y11>88</y11>
      <x12>182</x12>
      <y12>86</y12>
    </polygon>
  </object>
</annotation>
