<?xml version="1.0" ?>
<annotation>
  <folder>VOC</folder>
  <filename>0156.png</filename>
  <source>
    <database>roboflow.ai</database>
  </source>
  <size>
    <width>4032</width>
    <height>3024</height>
    <depth>3</depth>
  </size>
  <segmented>0</segmented>
  <object>
    <name>number plate</name>
    <bndbox>
      <xmin>1454</xmin>
      <ymin>1197</ymin>
      <xmax>1548</xmax>
      <ymax>1253</ymax>
    </bndbox>
    <polygon>
      <x1>1460</x1>
      <y1>1203</y1>
      <x2>1454</x2>
      <y2>1233</y2>
      <x3>1455</x3>
      <y3>1238</y3>
      <x4>1458</x4>
      <y4>1240</y4>
      <x5>1470</x5>
      <y5>1244</y5>
      <x6>1511</x6>
      <y6>1250</y6>
      <x7>1523</x7>
      <y7>1253</y7>
      <x8>1537</x8>
      <y8>1253</y8>
      <x9>1544</x9>
      <y9>1249</y9>
      <x10>1546</x10>
      <y10>1242</y10>
      <x11>1548</x11>
      <y11>1217</y11>
      <x12>1547</x12>
      <y12>1214</y12>
      <x13>1543</x13>
      <y13>1210</y13>
      <x14>1538</x14>
      <y14>1208</y14>
      <x15>1489</x15>
      <y15>1201</y15>
      <x16>1477</x16>
      <y16>1197</y16>
      <x17>1467</x17>
      <y17>1197</y17>
      <x18>1463</x18>
      <y18>1199</y18>
    </polygon>
  </object>
  <object>
    <name>number plate</name>
    <bndbox>
      <xmin>1036</xmin>
      <ymin>817</ymin>
      <xmax>1668</xmax>
      <ymax>1313</ymax>
    </bndbox>
    <polygon>
      <x1>1076</x1>
      <y1>886</y1>
      <x2>1061</x2>
      <y2>924</y2>
      <x3>1060</x3>
      <y3>931</y3>
      <x4>1058</x4>
      <y4>935</y4>
      <x5>1056</x5>
      <y5>962</y5>
      <x6>1048</x6>
      <y6>986</y6>
      <x7>1047</x7>
      <y7>1000</y7>
      <x8>1046</x8>
      <y8>1001</y8>
      <x9>1045</x9>
      <y9>1012</y9>
      <x10>1044</x10>
      <y10>1013</y10>
      <x11>1043</x11>
      <y11>1034</y11>
      <x12>1042</x12>
      <y12>1035</y12>
      <x13>1041</x13>
      <y13>1048</y13>
      <x14>1040</x14>
      <y14>1049</y14>
      <x15>1040</x15>
      <y15>1053</y15>
      <x16>1038</x16>
      <y16>1059</y16>
      <x17>1038</x17>
      <y17>1081</y17>
      <x18>1036</x18>
      <y18>1088</y18>
      <x19>1036</x19>
      <y19>1096</y19>
      <x20>1043</x20>
      <y20>1108</y20>
      <x21>1046</x21>
      <y21>1111</y21>
      <x22>1051</x22>
      <y22>1113</y22>
      <x23>1057</x23>
      <y23>1113</y23>
      <x24>1058</x24>
      <y24>1114</y24>
      <x25>1077</x25>
      <y25>1113</y25>
      <x26>1082</x26>
      <y26>1111</y26>
      <x27>1092</x27>
      <y27>1104</y27>
      <x28>1096</x28>
      <y28>1105</y28>
      <x29>1109</x29>
      <y29>1113</y29>
      <x30>1140</x30>
      <y30>1143</y30>
      <x31>1144</x31>
      <y31>1146</y31>
      <x32>1146</x32>
      <y32>1146</y32>
      <x33>1155</x33>
      <y33>1151</y33>
      <x34>1166</x34>
      <y34>1159</y34>
      <x35>1171</x35>
      <y35>1167</y35>
      <x36>1173</x36>
      <y36>1174</y36>
      <x37>1172</x37>
      <y37>1188</y37>
      <x38>1173</x38>
      <y38>1189</y38>
      <x39>1173</x39>
      <y39>1195</y39>
      <x40>1175</x40>
      <y40>1201</y40>
      <x41>1175</x41>
      <y41>1219</y41>
      <x42>1176</x42>
      <y42>1220</y42>
      <x43>1176</x43>
      <y43>1223</y43>
      <x44>1182</x44>
      <y44>1235</y44>
      <x45>1188</x45>
      <y45>1241</y45>
      <x46>1194</x46>
      <y46>1243</y46>
      <x47>1198</x47>
      <y47>1243</y47>
      <x48>1199</x48>
      <y48>1244</y48>
      <x49>1209</x49>
      <y49>1244</y49>
      <x50>1219</x50>
      <y50>1239</y50>
      <x51>1234</x51>
      <y51>1224</y51>
      <x52>1237</x52>
      <y52>1224</y52>
      <x53>1243</x53>
      <y53>1228</y53>
      <x54>1250</x54>
      <y54>1230</y54>
      <x55>1254</x55>
      <y55>1230</y55>
      <x56>1268</x56>
      <y56>1237</y56>
      <x57>1281</x57>
      <y57>1238</y57>
      <x58>1292</x58>
      <y58>1243</y58>
      <x59>1302</x59>
      <y59>1245</y59>
      <x60>1306</x60>
      <y60>1247</y60>
      <x61>1318</x61>
      <y61>1249</y61>
      <x62>1319</x62>
      <y62>1250</y62>
      <x63>1330</x63>
      <y63>1251</y63>
      <x64>1334</x64>
      <y64>1253</y64>
      <x65>1351</x65>
      <y65>1256</y65>
      <x66>1368</x66>
      <y66>1261</y66>
      <x67>1385</x67>
      <y67>1262</y67>
      <x68>1386</x68>
      <y68>1263</y68>
      <x69>1392</x69>
      <y69>1263</y69>
      <x70>1393</x70>
      <y70>1264</y70>
      <x71>1408</x71>
      <y71>1264</y71>
      <x72>1432</x72>
      <y72>1271</y72>
      <x73>1456</x73>
      <y73>1273</y73>
      <x74>1457</x74>
      <y74>1274</y74>
      <x75>1470</x75>
      <y75>1276</y75>
      <x76>1471</x76>
      <y76>1277</y76>
      <x77>1491</x77>
      <y77>1279</y77>
      <x78>1504</x78>
      <y78>1283</y78>
      <x79>1519</x79>
      <y79>1283</y79>
      <x80>1520</x80>
      <y80>1284</y80>
      <x81>1525</x81>
      <y81>1284</y81>
      <x82>1526</x82>
      <y82>1285</y82>
      <x83>1536</x83>
      <y83>1286</y83>
      <x84>1537</x84>
      <y84>1287</y84>
      <x85>1561</x85>
      <y85>1287</y85>
      <x86>1562</x86>
      <y86>1288</y86>
      <x87>1566</x87>
      <y87>1288</y87>
      <x88>1568</x88>
      <y88>1289</y88>
      <x89>1580</x89>
      <y89>1302</y89>
      <x90>1585</x90>
      <y90>1304</y90>
      <x91>1590</x91>
      <y91>1304</y91>
      <x92>1591</x92>
      <y92>1305</y92>
      <x93>1595</x93>
      <y93>1305</y93>
      <x94>1601</x94>
      <y94>1307</y94>
      <x95>1612</x95>
      <y95>1313</y95>
      <x96>1613</x96>
      <y96>1312</y96>
      <x97>1616</x97>
      <y97>1312</y97>
      <x98>1621</x98>
      <y98>1308</y98>
      <x99>1628</x99>
      <y99>1306</y99>
      <x100>1637</x100>
      <y100>1297</y100>
      <x101>1637</x101>
      <y101>1295</y101>
      <x102>1643</x102>
      <y102>1283</y102>
      <x103>1652</x103>
      <y103>1270</y103>
      <x104>1655</x104>
      <y104>1258</y104>
      <x105>1660</x105>
      <y105>1249</y105>
      <x106>1662</x106>
      <y106>1237</y106>
      <x107>1663</x107>
      <y107>1236</y107>
      <x108>1663</x108>
      <y108>1226</y108>
      <x109>1664</x109>
      <y109>1225</y109>
      <x110>1664</x110>
      <y110>1217</y110>
      <x111>1665</x111>
      <y111>1216</y111>
      <x112>1665</x112>
      <y112>1209</y112>
      <x113>1666</x113>
      <y113>1208</y113>
      <x114>1665</x114>
      <y114>1182</y114>
      <x115>1666</x115>
      <y115>1181</y115>
      <x116>1666</x116>
      <y116>1172</y116>
      <x117>1667</x117>
      <y117>1171</y117>
      <x118>1667</x118>
      <y118>1163</y118>
      <x119>1668</x119>
      <y119>1162</y119>
      <x120>1668</x120>
      <y120>1152</y120>
      <x121>1667</x121>
      <y121>1151</y121>
      <x122>1666</x122>
      <y122>1140</y122>
      <x123>1663</x123>
      <y123>1134</y123>
      <x124>1657</x124>
      <y124>1126</y124>
      <x125>1651</x125>
      <y125>1112</y125>
      <x126>1633</x126>
      <y126>1091</y126>
      <x127>1626</x127>
      <y127>1080</y127>
      <x128>1625</x128>
      <y128>1077</y128>
      <x129>1625</x129>
      <y129>1069</y129>
      <x130>1624</x130>
      <y130>1068</y130>
      <x131>1623</x131>
      <y131>1061</y131>
      <x132>1628</x132>
      <y132>1057</y132>
      <x133>1631</x133>
      <y133>1047</y133>
      <x134>1629</x134>
      <y134>1033</y134>
      <x135>1628</x135>
      <y135>1032</y135>
      <x136>1618</x136>
      <y136>1032</y136>
      <x137>1617</x137>
      <y137>1033</y137>
      <x138>1613</x138>
      <y138>1032</y138>
      <x139>1610</x139>
      <y139>1029</y139>
      <x140>1600</x140>
      <y140>1024</y140>
      <x141>1595</x141>
      <y141>1019</y141>
      <x142>1580</x142>
      <y142>995</y142>
      <x143>1578</x143>
      <y143>990</y143>
      <x144>1568</x144>
      <y144>976</y144>
      <x145>1562</x145>
      <y145>963</y145>
      <x146>1554</x146>
      <y146>954</y146>
      <x147>1541</x147>
      <y147>929</y147>
      <x148>1525</x148>
      <y148>914</y148>
      <x149>1519</x149>
      <y149>910</y149>
      <x150>1509</x150>
      <y150>906</y150>
      <x151>1491</x151>
      <y151>893</y151>
      <x152>1486</x152>
      <y152>891</y152>
      <x153>1481</x153>
      <y153>891</y153>
      <x154>1474</x154>
      <y154>888</y154>
      <x155>1472</x155>
      <y155>885</y155>
      <x156>1470</x156>
      <y156>874</y156>
      <x157>1463</x157>
      <y157>871</y157>
      <x158>1450</x158>
      <y158>860</y158>
      <x159>1442</x159>
      <y159>856</y159>
      <x160>1435</x160>
      <y160>856</y160>
      <x161>1426</x161>
      <y161>859</y161>
      <x162>1416</x162>
      <y162>858</y162>
      <x163>1398</x163>
      <y163>853</y163>
      <x164>1389</x164>
      <y164>848</y164>
      <x165>1375</x165>
      <y165>846</y165>
      <x166>1374</x166>
      <y166>845</y166>
      <x167>1355</x167>
      <y167>841</y167>
      <x168>1351</x168>
      <y168>839</y168>
      <x169>1344</x169>
      <y169>838</y169>
      <x170>1329</x170>
      <y170>833</y170>
      <x171>1298</x171>
      <y171>829</y171>
      <x172>1295</x172>
      <y172>827</y172>
      <x173>1283</x173>
      <y173>823</y173>
      <x174>1265</x174>
      <y174>822</y174>
      <x175>1264</x175>
      <y175>821</y175>
      <x176>1242</x176>
      <y176>819</y176>
      <x177>1235</x177>
      <y177>817</y177>
      <x178>1215</x178>
      <y178>817</y178>
      <x179>1206</x179>
      <y179>820</y179>
      <x180>1171</x180>
      <y180>819</y180>
      <x181>1163</x181>
      <y181>823</y181>
      <x182>1158</x182>
      <y182>824</y182>
      <x183>1145</x183>
      <y183>831</y183>
      <x184>1140</x184>
      <y184>836</y184>
      <x185>1135</x185>
      <y185>844</y185>
      <x186>1126</x186>
      <y186>853</y186>
      <x187>1121</x187>
      <y187>856</y187>
      <x188>1108</x188>
      <y188>869</y188>
      <x189>1090</x189>
      <y189>876</y189>
      <x190>1080</x190>
      <y190>882</y190>
    </polygon>
  </object>
</annotation>
