<?xml version="1.0" ?>
<annotation>
  <folder>VOC</folder>
  <filename>0217.jpg</filename>
  <source>
    <database>roboflow.ai</database>
  </source>
  <size>
    <width>278</width>
    <height>265</height>
    <depth>3</depth>
  </size>
  <segmented>0</segmented>
  <object>
    <name>number plate</name>
    <bndbox>
      <xmin>76</xmin>
      <ymin>95</ymin>
      <xmax>175</xmax>
      <ymax>159</ymax>
    </bndbox>
    <polygon>
      <x1>78</x1>
      <y1>97</y1>
      <x2>76</x2>
      <y2>127</y2>
      <x3>76</x3>
      <y3>147</y3>
      <x4>78</x4>
      <y4>149</y4>
      <x5>131</x5>
      <y5>155</y5>
      <x6>144</x6>
      <y6>155</y6>
      <x7>170</x7>
      <y7>159</y7>
      <x8>175</x8>
      <y8>157</y8>
      <x9>175</x9>
      <y9>104</y9>
      <x10>169</x10>
      <y10>102</y10>
      <x11>131</x11>
      <y11>100</y11>
      <x12>80</x12>
      <y12>95</y12>
    </polygon>
  </object>
</annotation>
