<?xml version="1.0" ?>
<annotation>
  <folder>VOC</folder>
  <filename>0174.png</filename>
  <source>
    <database>roboflow.ai</database>
  </source>
  <size>
    <width>3024</width>
    <height>4032</height>
    <depth>3</depth>
  </size>
  <segmented>0</segmented>
  <object>
    <name>number plate</name>
    <bndbox>
      <xmin>851</xmin>
      <ymin>2475</ymin>
      <xmax>1513</xmax>
      <ymax>2787</ymax>
    </bndbox>
    <polygon>
      <x1>853</x1>
      <y1>2483</y1>
      <x2>851</x2>
      <y2>2491</y2>
      <x3>851</x3>
      <y3>2509</y3>
      <x4>853</x4>
      <y4>2525</y4>
      <x5>855</x5>
      <y5>2601</y5>
      <x6>858</x6>
      <y6>2623</y6>
      <x7>858</x7>
      <y7>2640</y7>
      <x8>862</x8>
      <y8>2652</y8>
      <x9>866</x9>
      <y9>2676</y9>
      <x10>871</x10>
      <y10>2737</y10>
      <x11>875</x11>
      <y11>2747</y11>
      <x12>887</x12>
      <y12>2759</y12>
      <x13>891</x13>
      <y13>2761</y13>
      <x14>904</x14>
      <y14>2760</y14>
      <x15>923</x15>
      <y15>2764</y15>
      <x16>966</x16>
      <y16>2765</y16>
      <x17>990</x17>
      <y17>2770</y17>
      <x18>997</x18>
      <y18>2773</y18>
      <x19>1011</x19>
      <y19>2770</y19>
      <x20>1022</x20>
      <y20>2770</y20>
      <x21>1030</x21>
      <y21>2772</y21>
      <x22>1049</x22>
      <y22>2771</y22>
      <x23>1058</x23>
      <y23>2773</y23>
      <x24>1113</x24>
      <y24>2773</y24>
      <x25>1123</x25>
      <y25>2777</y25>
      <x26>1130</x26>
      <y26>2777</y26>
      <x27>1138</x27>
      <y27>2774</y27>
      <x28>1148</x28>
      <y28>2774</y28>
      <x29>1159</x29>
      <y29>2777</y29>
      <x30>1176</x30>
      <y30>2777</y30>
      <x31>1187</x31>
      <y31>2780</y31>
      <x32>1210</x32>
      <y32>2779</y32>
      <x33>1217</x33>
      <y33>2781</y33>
      <x34>1243</x34>
      <y34>2782</y34>
      <x35>1330</x35>
      <y35>2781</y35>
      <x36>1361</x36>
      <y36>2782</y36>
      <x37>1372</x37>
      <y37>2784</y37>
      <x38>1399</x38>
      <y38>2784</y38>
      <x39>1411</x39>
      <y39>2786</y39>
      <x40>1452</x40>
      <y40>2785</y40>
      <x41>1493</x41>
      <y41>2787</y41>
      <x42>1505</x42>
      <y42>2783</y42>
      <x43>1509</x43>
      <y43>2778</y43>
      <x44>1513</x44>
      <y44>2764</y44>
      <x45>1513</x45>
      <y45>2744</y45>
      <x46>1511</x46>
      <y46>2735</y46>
      <x47>1512</x47>
      <y47>2684</y47>
      <x48>1510</x48>
      <y48>2672</y48>
      <x49>1510</x49>
      <y49>2655</y49>
      <x50>1512</x50>
      <y50>2642</y50>
      <x51>1511</x51>
      <y51>2585</y51>
      <x52>1513</x52>
      <y52>2570</y52>
      <x53>1511</x53>
      <y53>2561</y53>
      <x54>1512</x54>
      <y54>2542</y54>
      <x55>1510</x55>
      <y55>2534</y55>
      <x56>1510</x56>
      <y56>2493</y56>
      <x57>1506</x57>
      <y57>2485</y57>
      <x58>1503</x58>
      <y58>2483</y58>
      <x59>1493</x59>
      <y59>2481</y59>
      <x60>1421</x60>
      <y60>2481</y60>
      <x61>1401</x61>
      <y61>2483</y61>
      <x62>1378</x62>
      <y62>2480</y62>
      <x63>1158</x63>
      <y63>2480</y63>
      <x64>1130</x64>
      <y64>2478</y64>
      <x65>1014</x65>
      <y65>2479</y65>
      <x66>1003</x66>
      <y66>2477</y66>
      <x67>947</x67>
      <y67>2480</y67>
      <x68>940</x68>
      <y68>2478</y68>
      <x69>920</x69>
      <y69>2478</y69>
      <x70>909</x70>
      <y70>2475</y70>
      <x71>860</x71>
      <y71>2477</y71>
    </polygon>
  </object>
  <object>
    <name>number plate</name>
    <bndbox>
      <xmin>2657</xmin>
      <ymin>2642</ymin>
      <xmax>3023</xmax>
      <ymax>2898</ymax>
    </bndbox>
    <polygon>
      <x1>3023</x1>
      <y1>2648</y1>
      <x2>3021</x2>
      <y2>2648</y2>
      <x3>3017</x3>
      <y3>2643</y3>
      <x4>3007</x4>
      <y4>2642</y4>
      <x5>3006</x5>
      <y5>2643</y5>
      <x6>2976</x6>
      <y6>2643</y6>
      <x7>2941</x7>
      <y7>2647</y7>
      <x8>2835</x8>
      <y8>2650</y8>
      <x9>2834</x9>
      <y9>2651</y9>
      <x10>2806</x10>
      <y10>2652</y10>
      <x11>2797</x11>
      <y11>2654</y11>
      <x12>2777</x12>
      <y12>2652</y12>
      <x13>2769</x13>
      <y13>2654</y13>
      <x14>2753</x14>
      <y14>2654</y14>
      <x15>2752</x15>
      <y15>2655</y15>
      <x16>2683</x16>
      <y16>2655</y16>
      <x17>2682</x17>
      <y17>2656</y17>
      <x18>2672</x18>
      <y18>2656</y18>
      <x19>2664</x19>
      <y19>2659</y19>
      <x20>2657</x20>
      <y20>2667</y20>
      <x21>2663</x21>
      <y21>2732</y21>
      <x22>2667</x22>
      <y22>2741</y22>
      <x23>2670</x23>
      <y23>2758</y23>
      <x24>2681</x24>
      <y24>2844</y24>
      <x25>2686</x25>
      <y25>2862</y25>
      <x26>2695</x26>
      <y26>2878</y26>
      <x27>2703</x27>
      <y27>2887</y27>
      <x28>2718</x28>
      <y28>2896</y28>
      <x29>2725</x29>
      <y29>2897</y29>
      <x30>2884</x30>
      <y30>2898</y30>
      <x31>2885</x31>
      <y31>2897</y31>
      <x32>2905</x32>
      <y32>2897</y32>
      <x33>2906</x33>
      <y33>2896</y33>
      <x34>3014</x34>
      <y34>2896</y34>
      <x35>3019</x35>
      <y35>2894</y35>
      <x36>3023</x36>
      <y36>2891</y36>
    </polygon>
  </object>
</annotation>
